gtt/__init__.py
gtt/byte_formatting.py
gtt/enums.py
gtt/exceptions.py
gtt/gtt_display.py
gtt/models.py
gtt_drivers-0.0.1.dist-info/LICENSE
gtt_drivers-0.0.1.dist-info/METADATA
gtt_drivers-0.0.1.dist-info/WHEEL
gtt_drivers-0.0.1.dist-info/top_level.txt
gtt_drivers-0.0.1.dist-info/RECORD
