Metadata-Version: 2.1
Name: gtt-drivers
Version: 0.0.1
Summary: A driver package for the Matrix Orbital's GTT series of displays
Home-page: https://github.com/Yook74/gtt-drivers
Author: Yook74
Author-email: andrewBlomen@gmail.com
License: UNKNOWN
Platform: UNKNOWN
License-File: LICENSE
Requires-Dist: pyserial
